easy_plot/__init__.py
easy_plot_nass/__init__.py
easy_plot_nass/code.py
easy_plot_nass-1.0.3.dist-info/LICENSE
easy_plot_nass-1.0.3.dist-info/METADATA
easy_plot_nass-1.0.3.dist-info/WHEEL
easy_plot_nass-1.0.3.dist-info/top_level.txt
easy_plot_nass-1.0.3.dist-info/RECORD
