Metadata-Version: 2.1
Name: easy_plot_nass
Version: 1.0.3
Summary: A simple module for creating plots with Matplotlib.
Home-page: https://github.com/NassAbd/easy_plot
Author: Abdallah Nassur
Author-email: nassur1607@gmail.com
Classifier: Programming Language :: Python :: 3
Classifier: License :: OSI Approved :: MIT License
Classifier: Operating System :: OS Independent
Requires-Python: >=3.6
License-File: LICENSE
Requires-Dist: matplotlib >=3.0
